README.rst
setup.py
pywayback.egg-info/PKG-INFO
pywayback.egg-info/SOURCES.txt
pywayback.egg-info/dependency_links.txt
pywayback.egg-info/entry_points.txt
pywayback.egg-info/requires.txt
pywayback.egg-info/top_level.txt
pywayback.egg-info/zip-safe
pywb/__init__.py
pywb/default_config.yaml
pywb/rules.yaml
pywb/apps/__init__.py
pywb/apps/cdx_server.py
pywb/apps/cli.py
pywb/apps/live_rewrite_server.py
pywb/apps/wayback.py
pywb/cdx/__init__.py
pywb/cdx/cdxdomainspecific.py
pywb/cdx/cdxobject.py
pywb/cdx/cdxops.py
pywb/cdx/cdxserver.py
pywb/cdx/cdxsource.py
pywb/cdx/query.py
pywb/cdx/zipnum.py
pywb/framework/__init__.py
pywb/framework/archivalrouter.py
pywb/framework/basehandlers.py
pywb/framework/cache.py
pywb/framework/memento.py
pywb/framework/proxy.py
pywb/framework/proxy_resolvers.py
pywb/framework/wbrequestresponse.py
pywb/framework/wsgi_wrappers.py
pywb/manager/__init__.py
pywb/manager/autoindex.py
pywb/manager/manager.py
pywb/manager/migrate.py
pywb/perms/__init__.py
pywb/perms/perms_filter.py
pywb/perms/perms_handler.py
pywb/rewrite/__init__.py
pywb/rewrite/cookie_rewriter.py
pywb/rewrite/header_rewriter.py
pywb/rewrite/html_rewriter.py
pywb/rewrite/regex_rewriters.py
pywb/rewrite/rewrite_content.py
pywb/rewrite/rewrite_live.py
pywb/rewrite/rewriterules.py
pywb/rewrite/url_rewriter.py
pywb/rewrite/wburl.py
pywb/static/default_banner.js
pywb/static/vidrw.js
pywb/static/wb.css
pywb/static/wb.js
pywb/static/wb_frame.js
pywb/static/wombat.js
pywb/static/flowplayer/flowplayer-3.2.18.swf
pywb/static/flowplayer/flowplayer.audio-3.2.11.swf
pywb/static/flowplayer/flowplayer.controls-3.2.16.swf
pywb/static/flowplayer/flowplayer.pseudostreaming-3.2.13.swf
pywb/static/flowplayer/toolbox.flashembed.js
pywb/templates/banner.html
pywb/templates/error.html
pywb/templates/frame_insert.html
pywb/templates/head_insert.html
pywb/templates/index.html
pywb/templates/not_found.html
pywb/templates/proxy_cert_download.html
pywb/templates/proxy_select.html
pywb/templates/query.html
pywb/templates/search.html
pywb/utils/__init__.py
pywb/utils/binsearch.py
pywb/utils/bufferedreaders.py
pywb/utils/canonicalize.py
pywb/utils/dsrules.py
pywb/utils/loaders.py
pywb/utils/statusandheaders.py
pywb/utils/timeutils.py
