Metadata-Version: 1.1
Name: pywayback
Version: 0.10.9.1
Summary: Python WayBack for web archive replay and live web proxy
Home-page: https://github.com/ikreymer/pywb
Author: Ilya Kreymer
Author-email: ikreymer@gmail.com
License: GPL
Platform: UNKNOWN
Classifier: Development Status :: 4 - Beta
Classifier: Environment :: Web Environment
Classifier: License :: OSI Approved :: GNU General Public License (GPL)
Classifier: License :: OSI Approved :: GNU General Public License v3 (GPLv3)
Classifier: Programming Language :: Python :: 2.6
Classifier: Programming Language :: Python :: 2.7
Classifier: Topic :: Internet :: Proxy Servers
Classifier: Topic :: Internet :: WWW/HTTP
Classifier: Topic :: Internet :: WWW/HTTP :: WSGI
Classifier: Topic :: Internet :: WWW/HTTP :: WSGI :: Application
Classifier: Topic :: Internet :: WWW/HTTP :: WSGI :: Middleware
Classifier: Topic :: Internet :: WWW/HTTP :: WSGI :: Server
Classifier: Topic :: Software Development :: Libraries :: Python Modules
Classifier: Topic :: System :: Archiving
Classifier: Topic :: System :: Archiving :: Backup
Classifier: Topic :: Utilities
Provides: pywb
Provides: pywb.utils
Provides: pywb.cdx
Provides: pywb.warc
Provides: pywb.rewrite
Provides: pywb.framework
Provides: pywb.manager
Provides: pywb.perms
Provides: pywb.webapp
Provides: pywb.apps
